quads_lib/__init__.py
quads_lib/base.py
quads_lib/decorators.py
quads_lib/exceptions.py
quads_lib/quads.py
quads_lib-0.2.0.dist-info/licenses/AUTHORS.rst
quads_lib-0.2.0.dist-info/licenses/LICENSE
quads_lib-0.2.0.dist-info/METADATA
quads_lib-0.2.0.dist-info/WHEEL
quads_lib-0.2.0.dist-info/top_level.txt
quads_lib-0.2.0.dist-info/RECORD
