Metadata-Version: 2.4
Name: quads-lib
Version: 0.2.0
Summary: Python client library for interacting with the QUADS API
Home-page: https://github.com/quadsproject/python-quads-lib
Author: Gonzalo Rafuls
Author-email: gonza@redhat.com
License: LGPL-3.0-only
Project-URL: Documentation, https://python-quads-lib.readthedocs.io/
Project-URL: Changelog, https://python-quads-lib.readthedocs.io/en/latest/changelog.html
Project-URL: Issue Tracker, https://github.com/quadsproject/python-quads-lib/issues
Classifier: Development Status :: 5 - Production/Stable
Classifier: Intended Audience :: Developers
Classifier: Operating System :: Unix
Classifier: Operating System :: POSIX
Classifier: Operating System :: Microsoft :: Windows
Classifier: Programming Language :: Python
Classifier: Programming Language :: Python :: 3
Classifier: Programming Language :: Python :: 3 :: Only
Classifier: Programming Language :: Python :: 3.9
Classifier: Programming Language :: Python :: 3.10
Classifier: Programming Language :: Python :: 3.11
Classifier: Programming Language :: Python :: 3.12
Classifier: Programming Language :: Python :: Implementation :: CPython
Classifier: Programming Language :: Python :: Implementation :: PyPy
Classifier: Topic :: Utilities
Requires-Python: >=3.9
License-File: LICENSE
License-File: AUTHORS.rst
Requires-Dist: requests>=2.31.0
Dynamic: author
Dynamic: author-email
Dynamic: classifier
Dynamic: description
Dynamic: home-page
Dynamic: license
Dynamic: license-file
Dynamic: project-url
Dynamic: requires-dist
Dynamic: requires-python
Dynamic: summary
